{
  "id": "forearms_reverse_curl",
  "name": "Barbell Reverse Wrist Curl",
  "category": "forearms",
  "primary_muscles": [
    "forearm_extensors"
  ],
  "secondary_muscles": [],
  "equipment": "barbell",
  "difficulty": "beginner",
  "movement_pattern": "wrist_extension",
  "mechanics": "isolation",
  "aliases": [
    "Reverse Wrist Curl"
  ],
  "hypertrophy_rep_range": {
    "min": 8,
    "max": 15
  },
  "rest_time": {
    "min_seconds": 60,
    "max_seconds": 90,
    "label": "60-90s"
  },
  "breathing": "Exhale on concentric, inhale on eccentric",
  "cues": [],
  "common_mistakes": [],
  "alternatives": [],
  "tempo": "2-1-2",
  "movement_plane": "multi_planar",
  "stability_requirement": "low",
  "skill_requirement": "low",
  "fatigue_score": 3.0,
  "systemic_fatigue": "low",
  "joint_stress": {
    "overall": "moderate",
    "notes": ""
  },
  "force_curve": "flat",
  "resistance_profile": "constant",
  "unilateral_bilateral": "bilateral",
  "recommended_rir": {
    "min": 2,
    "max": 3,
    "description": "Leave 2-3 reps in reserve for safety"
  },
  "muscle_contributions": [
    {
      "muscle_id": "forearm_extensors",
      "percentage": 100.0
    }
  ],
  "tags": [],
  "knowledge_version": "1.0.0",
  "last_updated": "2026-07-02",
  "references": []
}
